bdd_trace/__init__.py
bdd_trace/log.py
bdd_trace/py.typed
bdd_trace/trace.py
bdd_trace-0.5.7.dist-info/WHEEL
bdd_trace-0.5.7.dist-info/METADATA
bdd_trace-0.5.7.dist-info/RECORD
