Metadata-Version: 2.3
Name: bdd-trace
Version: 0.5.7
Summary: BDD项目日志和追踪SDK
Author: 蔡涛
Author-email: 蔡涛 <caitao@zhejianglab.cn>
Requires-Dist: opentelemetry-exporter-otlp>=1.36.0
Requires-Dist: opentelemetry-distro==0.57b0
Requires-Python: >=3.10
